omotes_simulator_core/__init__.py
omotes_simulator_core/__main__.py
omotes_simulator_core/py.typed
omotes_simulator_core/adapter/__init__.py
omotes_simulator_core/adapter/presentation/__init__.py
omotes_simulator_core/adapter/transforms/__init__.py
omotes_simulator_core/adapter/transforms/controller_mapper.py
omotes_simulator_core/adapter/transforms/esdl_asset_mapper.py
omotes_simulator_core/adapter/transforms/esdl_graph_mapper.py
omotes_simulator_core/adapter/transforms/mappers.py
omotes_simulator_core/adapter/transforms/string_to_esdl.py
omotes_simulator_core/adapter/transforms/transform_utils.py
omotes_simulator_core/adapter/transforms/controller_mappers/__init__.py
omotes_simulator_core/adapter/transforms/controller_mappers/controller_consumer_mapper.py
omotes_simulator_core/adapter/transforms/controller_mappers/controller_heat_transfer_mapper.py
omotes_simulator_core/adapter/transforms/controller_mappers/controller_producer_mapper.py
omotes_simulator_core/adapter/transforms/controller_mappers/controller_storage_mapper.py
omotes_simulator_core/adapter/transforms/esdl_asset_mappers/__init__.py
omotes_simulator_core/adapter/transforms/esdl_asset_mappers/ates_mapper.py
omotes_simulator_core/adapter/transforms/esdl_asset_mappers/consumer_mapper.py
omotes_simulator_core/adapter/transforms/esdl_asset_mappers/heat_exchanger_mapper.py
omotes_simulator_core/adapter/transforms/esdl_asset_mappers/heat_pump_mapper.py
omotes_simulator_core/adapter/transforms/esdl_asset_mappers/pipe_mapper.py
omotes_simulator_core/adapter/transforms/esdl_asset_mappers/producer_mapper.py
omotes_simulator_core/adapter/utility/__init__.py
omotes_simulator_core/adapter/utility/graph.py
omotes_simulator_core/entities/__init__.py
omotes_simulator_core/entities/esdl_object.py
omotes_simulator_core/entities/heat_network.py
omotes_simulator_core/entities/network_controller.py
omotes_simulator_core/entities/network_controller_abstract.py
omotes_simulator_core/entities/simulation_configuration.py
omotes_simulator_core-0.0.28.dist-info/LICENSE
omotes_simulator_core-0.0.28.dist-info/METADATA
omotes_simulator_core-0.0.28.dist-info/WHEEL
omotes_simulator_core-0.0.28.dist-info/top_level.txt
omotes_simulator_core-0.0.28.dist-info/RECORD
